mi_libreria_matematica/__init__.py
mi_libreria_matematica/operaciones.py
mi_libreria_matematica-0.1.0.dist-info/METADATA
mi_libreria_matematica-0.1.0.dist-info/WHEEL
mi_libreria_matematica-0.1.0.dist-info/top_level.txt
mi_libreria_matematica-0.1.0.dist-info/RECORD
