Metadata-Version: 2.1
Name: mi_libreria_matematica
Version: 0.1.0
Summary: Una librería de operaciones matemáticas básicas.
Author-email: Manuel Garcés <manugp1994@gmail.com>
License: MIT
Project-URL: Homepage, https://github.com/tuusuario/mi_libreria_matematica
Project-URL: Bug Tracker, https://github.com/tuusuario/mi_libreria_matematica/issues
Keywords: matematica,operaciones,python
Requires-Python: >=3.7
